rhapsody/VERSION
rhapsody/__init__.py
rhapsody/data.tar.gz
rhapsody/features/BLOSUM.py
rhapsody/features/EVmutation.py
rhapsody/features/PDB.py
rhapsody/features/Pfam.py
rhapsody/features/PolyPhen2.py
rhapsody/features/Uniprot.py
rhapsody/features/__init__.py
rhapsody/predict/__init__.py
rhapsody/predict/core.py
rhapsody/predict/figures.py
rhapsody/predict/main.py
rhapsody/train/RFtraining.py
rhapsody/train/__init__.py
rhapsody/train/figures.py
rhapsody/utils/__init__.py
rhapsody/utils/misc.py
rhapsody/utils/settings.py
prody_rhapsody-0.9.8.dist-info/LICENSE
prody_rhapsody-0.9.8.dist-info/METADATA
prody_rhapsody-0.9.8.dist-info/WHEEL
prody_rhapsody-0.9.8.dist-info/top_level.txt
prody_rhapsody-0.9.8.dist-info/RECORD
