Metadata-Version: 2.1
Name: prody-rhapsody
Version: 0.9.8
Summary: Python program, based on ProDy, for pathogenicity prediction
Home-page: https://github.com/prody/rhapsody
Author: Luca Ponzoni
Author-email: lponzoni@pitt.edu
License: GPL
Project-URL: Bug Reports, https://github.com/prody/rhapsody/issues
Project-URL: Source, https://github.com/prody/rhapsody/
Keywords: SAV missense variant protein dynamics
Platform: Windows
Platform: MacOS X
Platform: POSIX
Classifier: Development Status :: 4 - Beta
Classifier: Intended Audience :: End Users/Desktop
Classifier: Intended Audience :: Science/Research
Classifier: Topic :: Scientific/Engineering :: Bio-Informatics
Classifier: Operating System :: MacOS :: MacOS X
Classifier: Operating System :: Microsoft :: Windows
Classifier: Operating System :: POSIX
Classifier: License :: OSI Approved :: GNU General Public License v3 (GPLv3)
Classifier: Programming Language :: Python :: 3.6
Classifier: Programming Language :: Python :: 3.7
Requires-Python: >=3.6, <4
Requires-Dist: requests
Requires-Dist: tqdm
Requires-Dist: numpy
Requires-Dist: scikit-learn
Requires-Dist: matplotlib
Requires-Dist: biopython
Requires-Dist: pyparsing
Requires-Dist: prody
Provides-Extra: docs
Requires-Dist: sphinx (>=1.4) ; extra == 'docs'
Requires-Dist: sphinx-theme ; extra == 'docs'
Requires-Dist: sphinx-rtd-theme ; extra == 'docs'
